{
  "ALBANIA": 102,
  "ANDORRA": 46,
  "ARGENTINA": 52,
  "AUSTRIA": 5,
  "BELGIUM": 6,
  "BRASIL": 87,
  "BULGARIA": 9,
  "CAMEROUN": 94,
  "CANADA": 10,
  "CHILE": 98,
  "COLOMBIE": 68,
  "CZECH REPUBLIC": 34,
  "DENMARK": 12,
  "ESTONIA": 15,
  "FINLAND": 17,
  "FRANCE": 18,
  "GERMANY": 1,
  "GIBRALTAR": 56,
  "GREECE": 19,
  "HUNGARY": 21,
  "ICELAND": 85,
  "ISRAEL": 63,
  "ITALY": 24,
  "JERSEY": 79,
  "LATVIA": 26,
  "LIECHTENSTEIN": 51,
  "LITHUANIA": 27,
  "LUXEMBOURG": 28,
  "MAROCCO": 74,
  "MEXICO": 59,
  "MOLDOVA": 101,
  "MONACO": 29,
  "NETHERLANDS": 31,
  "NORWAY": 30,
  "PEROU": 111,
  "POLAND": 32,
  "PORTUGAL": 33,
  "REPUBLIC OF MACEDONIA": 44,
  "ROMANIA": 35,
  "RUSSIA": 36,
  "SENEGAL": 95,
  "SLOVAKIA": 38,
  "SLOVENIA": 39,
  "SPAIN": 14,
  "SWEDEN": 40,
  "SWITZERLAND": 41,
  "TURKEY": 42,
  "UKRAINE": 48,
  "UNITED ARAB EMIRATES": 66,
  "UNITED STATES": 16
}